suit/__init__.py
suit/admin.py
suit/admin_filters.py
suit/apps.py
suit/compat.py
suit/config.py
suit/menu.py
suit/sortables.py
suit/template.py
suit/widgets.py
suit/static/admin/css/changelists.css
suit/static/admin/css/dashboard.css
suit/static/admin/css/forms.css
suit/static/admin/css/login.css
suit/static/suit/css/font-awesome.min.css
suit/static/suit/css/suit.css
suit/static/suit/css/suit.min.css
suit/static/suit/fonts/FontAwesome.otf
suit/static/suit/fonts/fontawesome-webfont.eot
suit/static/suit/fonts/fontawesome-webfont.svg
suit/static/suit/fonts/fontawesome-webfont.ttf
suit/static/suit/fonts/fontawesome-webfont.woff
suit/static/suit/fonts/fontawesome-webfont.woff2
suit/static/suit/js/autosize.min.js
suit/static/suit/js/suit.js
suit/static/suit/js/suit.sortables.js
suit/static/vendor/css/bootstrap-utilities.css
suit/static/vendor/css/bootstrap-utilities.css.map
suit/static/vendor/css/bootstrap-utilities.min.css
suit/static/vendor/css/bootstrap-utilities.min.css.map
suit/static/vendor/js/bootstrap.bundle.js
suit/static/vendor/js/bootstrap.bundle.js.map
suit/static/vendor/js/bootstrap.bundle.min.js
suit/static/vendor/js/bootstrap.bundle.min.js.map
suit/static/vendor/js/bootstrap.js
suit/static/vendor/js/bootstrap.js.map
suit/static/vendor/js/bootstrap.min.js
suit/static/vendor/js/bootstrap.min.js.map
suit/templates/admin/base.html
suit/templates/admin/base_site.html
suit/templates/admin/change_form.html
suit/templates/admin/change_list.html
suit/templates/admin/change_list_results.html
suit/templates/admin/filter_horizontal.html
suit/templates/admin/login.html
suit/templates/admin/auth/user/add_form.html
suit/templates/admin/auth/user/change_password.html
suit/templates/admin/includes/fieldset.html
suit/templates/registration/password_change_form.html
suit/templates/suit/change_form_includes.html
suit/templates/suit/menu.html
suit/templates/suit/menu_item.html
suit/templates/suit/nav_sidebar.html
suit/templates/suit/search_form.html
django_suit_v2_pm-2.4.dist-info/LICENSE
django_suit_v2_pm-2.4.dist-info/METADATA
django_suit_v2_pm-2.4.dist-info/WHEEL
django_suit_v2_pm-2.4.dist-info/top_level.txt
django_suit_v2_pm-2.4.dist-info/RECORD
